hypercore-0.0.1.dist-info/METADATA
hypercore-0.0.1.dist-info/WHEEL
hyperbee/__init__.py
hyperbee/hyperbee.py
hyperbee/libhyperbee.so
hypercore-0.0.1.dist-info/RECORD
