Metadata-Version: 2.3
Name: hypercore
Version: 0.0.1
Summary: Peer to Peer B-tree
Keywords: dat,p2p,btree,hypercore
License: MIT OR Apache-2.0
Project-URL: Source Code, https://github.com/cowlicks/hyperbee
